Replidec/Replidec.py
Replidec/Replidec_cmdline.py
Replidec/Replidec_multi.py
Replidec/__init__.py
Replidec/cli.py
Replidec/utility.py
replidec-0.3.5.dist-info/licenses/LICENSE
replidec-0.3.5.dist-info/METADATA
replidec-0.3.5.dist-info/WHEEL
replidec-0.3.5.dist-info/entry_points.txt
replidec-0.3.5.dist-info/top_level.txt
replidec-0.3.5.dist-info/zip-safe
replidec-0.3.5.dist-info/RECORD
