Metadata-Version: 2.4
Name: Replidec
Version: 0.3.5
Summary: Replication Cycle Decipher for Phages
Home-page: https://github.com/deng-lab/Replidec
Author: Xue Peng
Author-email: peng_sherry@outlook.com
License: MIT license
Keywords: Replidec
Classifier: Programming Language :: Python :: 3
Classifier: License :: OSI Approved :: MIT License
Classifier: Operating System :: OS Independent
Classifier: Topic :: Scientific/Engineering :: Bio-Informatics
Classifier: Intended Audience :: Science/Research
Requires-Python: >=3.8
License-File: LICENSE
Requires-Dist: biopython>=1.77
Requires-Dist: future>=0.18.2
Dynamic: author
Dynamic: author-email
Dynamic: classifier
Dynamic: description
Dynamic: description-content-type
Dynamic: home-page
Dynamic: keywords
Dynamic: license
Dynamic: license-file
Dynamic: requires-dist
Dynamic: requires-python
Dynamic: summary
